{
  "chainId": 97,
  "name": "BNB Smart Chain Testnet",
  "updatedAt": "2026-07-09T23:54:57.036Z",
  "rpcs": [
    {
      "url": "https://data-seed-prebsc-2-s3.bnbchain.org:8545",
      "score": 100,
      "alive": true,
      "latencyMs": {
        "p50": 42,
        "p95": 50
      },
      "blockLag": 0,
      "rateLimit": {
        "sustainableRps": 40,
        "throttled": false
      },
      "subScores": {
        "latency": 100,
        "freshness": 100,
        "rateLimit": 100
      },
      "errorKind": null
    },
    {
      "url": "https://data-seed-prebsc-2-s2.bnbchain.org:8545",
      "score": 97,
      "alive": true,
      "latencyMs": {
        "p50": 49,
        "p95": 64
      },
      "blockLag": 1,
      "rateLimit": {
        "sustainableRps": 40,
        "throttled": false
      },
      "subScores": {
        "latency": 100,
        "freshness": 90,
        "rateLimit": 100
      },
      "errorKind": null
    },
    {
      "url": "https://data-seed-prebsc-1-s3.bnbchain.org:8545",
      "score": 97,
      "alive": true,
      "latencyMs": {
        "p50": 33,
        "p95": 56
      },
      "blockLag": 1,
      "rateLimit": {
        "sustainableRps": 40,
        "throttled": false
      },
      "subScores": {
        "latency": 100,
        "freshness": 90,
        "rateLimit": 100
      },
      "errorKind": null
    },
    {
      "url": "https://data-seed-prebsc-1-s2.bnbchain.org:8545",
      "score": 88,
      "alive": true,
      "latencyMs": {
        "p50": 62,
        "p95": 94
      },
      "blockLag": 4,
      "rateLimit": {
        "sustainableRps": 40,
        "throttled": false
      },
      "subScores": {
        "latency": 100,
        "freshness": 60,
        "rateLimit": 100
      },
      "errorKind": null
    },
    {
      "url": "https://bsc-testnet-rpc.publicnode.com",
      "tracking": "none",
      "score": 82,
      "alive": true,
      "latencyMs": {
        "p50": 46,
        "p95": 553
      },
      "blockLag": 6,
      "rateLimit": {
        "sustainableRps": 40,
        "throttled": false
      },
      "subScores": {
        "latency": 100,
        "freshness": 40,
        "rateLimit": 100
      },
      "errorKind": null
    },
    {
      "url": "https://bsc-testnet.rpc.sentio.xyz",
      "tracking": "limited",
      "score": 82,
      "alive": true,
      "latencyMs": {
        "p50": 103,
        "p95": 117
      },
      "blockLag": 6,
      "rateLimit": {
        "sustainableRps": 40,
        "throttled": false
      },
      "subScores": {
        "latency": 100,
        "freshness": 40,
        "rateLimit": 100
      },
      "errorKind": null
    },
    {
      "url": "https://data-seed-prebsc-1-s1.bnbchain.org:8545",
      "score": 82,
      "alive": true,
      "latencyMs": {
        "p50": 30,
        "p95": 43
      },
      "blockLag": 6,
      "rateLimit": {
        "sustainableRps": 40,
        "throttled": false
      },
      "subScores": {
        "latency": 100,
        "freshness": 40,
        "rateLimit": 100
      },
      "errorKind": null
    },
    {
      "url": "https://data-seed-prebsc-2-s1.bnbchain.org:8545",
      "score": 82,
      "alive": true,
      "latencyMs": {
        "p50": 29,
        "p95": 31
      },
      "blockLag": 6,
      "rateLimit": {
        "sustainableRps": 40,
        "throttled": false
      },
      "subScores": {
        "latency": 100,
        "freshness": 40,
        "rateLimit": 100
      },
      "errorKind": null
    },
    {
      "url": "https://bsc-testnet.drpc.org",
      "tracking": "none",
      "score": 76,
      "alive": true,
      "latencyMs": {
        "p50": 48,
        "p95": 49
      },
      "blockLag": 8,
      "rateLimit": {
        "sustainableRps": 40,
        "throttled": false
      },
      "subScores": {
        "latency": 100,
        "freshness": 20,
        "rateLimit": 100
      },
      "errorKind": null
    },
    {
      "url": "https://api.zan.top/bsc-testnet",
      "tracking": "limited",
      "score": 55.6,
      "alive": true,
      "latencyMs": {
        "p50": 216,
        "p95": 216
      },
      "blockLag": 4,
      "rateLimit": {
        "sustainableRps": 0,
        "throttled": true
      },
      "subScores": {
        "latency": 94,
        "freshness": 60,
        "rateLimit": 0
      },
      "errorKind": "rate_limit"
    },
    {
      "url": "https://bnb-testnet.api.onfinality.io/public",
      "tracking": "limited",
      "score": 52,
      "alive": true,
      "latencyMs": {
        "p50": 42,
        "p95": 42
      },
      "blockLag": 6,
      "rateLimit": {
        "sustainableRps": 0,
        "throttled": true
      },
      "subScores": {
        "latency": 100,
        "freshness": 40,
        "rateLimit": 0
      },
      "errorKind": "rate_limit"
    },
    {
      "url": "https://endpoints.omniatech.io/v1/bsc/testnet/public",
      "tracking": "none",
      "score": 0,
      "alive": false,
      "latencyMs": null,
      "blockLag": null,
      "rateLimit": null,
      "subScores": {
        "latency": 0,
        "freshness": 0,
        "rateLimit": 0
      },
      "errorKind": "network"
    },
    {
      "url": "https://bsc-testnet.public.blastapi.io",
      "tracking": "limited",
      "score": 0,
      "alive": false,
      "latencyMs": null,
      "blockLag": null,
      "rateLimit": null,
      "subScores": {
        "latency": 0,
        "freshness": 0,
        "rateLimit": 0
      },
      "errorKind": "network"
    },
    {
      "url": "https://public.stackup.sh/api/v1/node/bsc-testnet",
      "tracking": "limited",
      "score": 0,
      "alive": false,
      "latencyMs": null,
      "blockLag": null,
      "rateLimit": null,
      "subScores": {
        "latency": 0,
        "freshness": 0,
        "rateLimit": 0
      },
      "errorKind": "network"
    },
    {
      "url": "https://bsc-testnet.4everland.org/v1/37fa9972c1b1cd5fab542c7bdd4cde2f",
      "tracking": "limited",
      "score": 0,
      "alive": false,
      "latencyMs": null,
      "blockLag": null,
      "rateLimit": null,
      "subScores": {
        "latency": 0,
        "freshness": 0,
        "rateLimit": 0
      },
      "errorKind": "network"
    },
    {
      "url": "https://bsc-testnet.therpc.io",
      "tracking": "limited",
      "score": 0,
      "alive": false,
      "latencyMs": null,
      "blockLag": null,
      "rateLimit": null,
      "subScores": {
        "latency": 0,
        "freshness": 0,
        "rateLimit": 0
      },
      "errorKind": "network"
    },
    {
      "url": "https://bsctestapi.terminet.io/rpc",
      "score": 0,
      "alive": false,
      "latencyMs": null,
      "blockLag": null,
      "rateLimit": null,
      "subScores": {
        "latency": 0,
        "freshness": 0,
        "rateLimit": 0
      },
      "errorKind": "timeout"
    }
  ]
}
